kframe/__about__.py
kframe/__init__.py
kframe/api/__init__.py
kframe/api/apitools.py
kframe/collections/__init__.py
kframe/collections/collections.py
kframe/config/__init__.py
kframe/config/configattr.py
kframe/config/configentity.py
kframe/model/__init__.py
kframe/model/managedb.py
kframe-0.5.3.dist-info/METADATA
kframe-0.5.3.dist-info/WHEEL
kframe-0.5.3.dist-info/licenses/LICENSE.txt
kframe-0.5.3.dist-info/RECORD
